nlpapi/__init__.py
nlpapi/__version__.py
nlpapi/cli.py
nlpapi-0.1.2.dist-info/LICENSE
nlpapi-0.1.2.dist-info/METADATA
nlpapi-0.1.2.dist-info/WHEEL
nlpapi-0.1.2.dist-info/entry_points.txt
nlpapi-0.1.2.dist-info/top_level.txt
nlpapi-0.1.2.dist-info/RECORD
